pymcversion/__init__.py
pymcversion/bedrock_server.py
pymcversion/ios_store_lookup.py
pymcversion/java_version_manifest.py
pymcversion/scripts/__init__.py
pymcversion/scripts/mcversion.py
pymcversion-20211023.1.dist-info/LICENSE
pymcversion-20211023.1.dist-info/METADATA
pymcversion-20211023.1.dist-info/WHEEL
pymcversion-20211023.1.dist-info/entry_points.txt
pymcversion-20211023.1.dist-info/top_level.txt
pymcversion-20211023.1.dist-info/RECORD
