Metadata-Version: 2.1
Name: pymcversion
Version: 20211023.1
Summary: Minecraft version info utility
Home-page: https://github.com/aoirint/pymcversion
Author: aoirint
Author-email: aoirint@gmail.com
License: UNKNOWN
Platform: UNKNOWN
Classifier: Development Status :: 3 - Alpha
Classifier: License :: OSI Approved :: The Unlicense (Unlicense)
Classifier: Programming Language :: Python
Classifier: Programming Language :: Python :: 3
Classifier: Programming Language :: Python :: 3.7
Classifier: Programming Language :: Python :: 3.8
Classifier: Programming Language :: Python :: 3.9
License-File: LICENSE
Requires-Dist: requests
Requires-Dist: pydantic
